{
  "scenario_id": "S-083",
  "title": "Aynı Dosyaya Zincirleme Çapraz Departman Erişimi",
  "mode": "negative",
  "category": "çapraz/multi-user",
  "user_role": "Satış",
  "deterministic_seed": 9083,
  "expected_severity": "ALERT",
  "feature_ids": [
    "F-073",
    "F-039",
    "F-037"
  ],
  "parity_level": "L2",
  "parity_target": "L2",
  "features_executed": [
    {
      "feature_id": "F-073",
      "result": "PASS",
      "parity_level": "L2",
      "actions_executed": [
        {
          "service": "suitecrm",
          "response": {
            "users": 1,
            "record_id": "contract-991"
          }
        },
        {
          "service": "wiki",
          "response": {
            "pages": 1
          }
        }
      ],
      "raw_logs_asserted": [
        {
          "path": "/home/caglarkc/Desktop/Github/all-agentics/watchtower-demo/server-stack/logs/suitecrm/crm.jsonl",
          "result": "PASS"
        }
      ],
      "ingest_assertions": [
        {
          "assertion": "L2:log-pipeline:corp-events:F-073",
          "elasticsearch": {
            "target": "http://172.28.0.17:9200",
            "cluster_status": "green",
            "result": "PASS"
          },
          "log_pipeline": {
            "target": "http://172.28.0.16:9201",
            "elasticsearch": "green",
            "result": "PASS"
          },
          "result": "PASS",
          "parity_level": "L2",
          "note": "RI-6: cluster healthy; L2 ingest gate",
          "ship": {
            "shipped": true,
            "indexed": 80,
            "index": "corp-logs-f-073",
            "pipeline": {
              "feature_id": "F-073",
              "index": "corp-logs-f-073",
              "indexed": 80
            }
          }
        }
      ],
      "seed_refs": [
        "seeds/real/hris/employees.yml",
        "seeds/real/badge/locations.yml",
        "seeds/real/print/confidential-report.pdf",
        "seeds/real/crm/records.yml"
      ]
    },
    {
      "feature_id": "F-039",
      "result": "PASS",
      "parity_level": "L3",
      "actions_executed": [
        {
          "service": "samba-files-actions",
          "response": {
            "renames": 1
          }
        }
      ],
      "raw_logs_asserted": [
        {
          "path": "/home/caglarkc/Desktop/Github/all-agentics/watchtower-demo/server-stack/logs/samba/audit.log",
          "result": "PASS"
        }
      ],
      "ingest_assertions": [
        {
          "assertion": "L3:elasticsearch:corp-logs-f-039",
          "elasticsearch": {
            "target": "http://172.28.0.17:9200",
            "cluster_status": "green",
            "result": "PASS"
          },
          "log_pipeline": {
            "target": "http://172.28.0.16:9201",
            "elasticsearch": "green",
            "result": "PASS"
          },
          "index_query": {
            "index": "corp-logs-f-039",
            "count": 2640,
            "result": "PASS"
          },
          "result": "PASS",
          "parity_level": "L3",
          "ship": {
            "shipped": true,
            "indexed": 80,
            "index": "corp-logs-f-039",
            "pipeline": {
              "feature_id": "F-039",
              "index": "corp-logs-f-039",
              "indexed": 80
            }
          }
        }
      ],
      "seed_refs": [
        "seeds/real/identity/users.csv",
        "seeds/real/files/classification.yml",
        "seeds/real/baseline/normal_day.yml"
      ]
    },
    {
      "feature_id": "F-037",
      "result": "PASS",
      "parity_level": "L3",
      "actions_executed": [
        {
          "service": "samba-files-actions",
          "response": {
            "cross_department": true
          }
        }
      ],
      "raw_logs_asserted": [
        {
          "path": "/home/caglarkc/Desktop/Github/all-agentics/watchtower-demo/server-stack/logs/samba/audit.log",
          "result": "PASS"
        }
      ],
      "ingest_assertions": [
        {
          "assertion": "L3:elasticsearch:corp-logs-f-037",
          "elasticsearch": {
            "target": "http://172.28.0.17:9200",
            "cluster_status": "green",
            "result": "PASS"
          },
          "log_pipeline": {
            "target": "http://172.28.0.16:9201",
            "elasticsearch": "green",
            "result": "PASS"
          },
          "index_query": {
            "index": "corp-logs-f-037",
            "count": 4560,
            "result": "PASS"
          },
          "result": "PASS",
          "parity_level": "L3",
          "ship": {
            "shipped": true,
            "indexed": 80,
            "index": "corp-logs-f-037",
            "pipeline": {
              "feature_id": "F-037",
              "index": "corp-logs-f-037",
              "indexed": 80
            }
          }
        }
      ],
      "seed_refs": [
        "seeds/real/identity/users.csv",
        "seeds/real/files/classification.yml",
        "seeds/real/baseline/normal_day.yml"
      ]
    }
  ],
  "actions_executed": [
    {
      "service": "suitecrm",
      "response": {
        "users": 1,
        "record_id": "contract-991"
      }
    },
    {
      "service": "wiki",
      "response": {
        "pages": 1
      }
    },
    {
      "service": "samba-files-actions",
      "response": {
        "renames": 1
      }
    },
    {
      "service": "samba-files-actions",
      "response": {
        "cross_department": true
      }
    }
  ],
  "raw_logs_asserted": [
    {
      "path": "/home/caglarkc/Desktop/Github/all-agentics/watchtower-demo/server-stack/logs/suitecrm/crm.jsonl",
      "result": "PASS"
    },
    {
      "path": "/home/caglarkc/Desktop/Github/all-agentics/watchtower-demo/server-stack/logs/samba/audit.log",
      "result": "PASS"
    },
    {
      "path": "/home/caglarkc/Desktop/Github/all-agentics/watchtower-demo/server-stack/logs/samba/audit.log",
      "result": "PASS"
    }
  ],
  "ingest_assertions": [
    {
      "assertion": "L2:log-pipeline:corp-events:F-073",
      "elasticsearch": {
        "target": "http://172.28.0.17:9200",
        "cluster_status": "green",
        "result": "PASS"
      },
      "log_pipeline": {
        "target": "http://172.28.0.16:9201",
        "elasticsearch": "green",
        "result": "PASS"
      },
      "result": "PASS",
      "parity_level": "L2",
      "note": "RI-6: cluster healthy; L2 ingest gate",
      "ship": {
        "shipped": true,
        "indexed": 80,
        "index": "corp-logs-f-073",
        "pipeline": {
          "feature_id": "F-073",
          "index": "corp-logs-f-073",
          "indexed": 80
        }
      }
    },
    {
      "assertion": "L3:elasticsearch:corp-logs-f-039",
      "elasticsearch": {
        "target": "http://172.28.0.17:9200",
        "cluster_status": "green",
        "result": "PASS"
      },
      "log_pipeline": {
        "target": "http://172.28.0.16:9201",
        "elasticsearch": "green",
        "result": "PASS"
      },
      "index_query": {
        "index": "corp-logs-f-039",
        "count": 2640,
        "result": "PASS"
      },
      "result": "PASS",
      "parity_level": "L3",
      "ship": {
        "shipped": true,
        "indexed": 80,
        "index": "corp-logs-f-039",
        "pipeline": {
          "feature_id": "F-039",
          "index": "corp-logs-f-039",
          "indexed": 80
        }
      }
    },
    {
      "assertion": "L3:elasticsearch:corp-logs-f-037",
      "elasticsearch": {
        "target": "http://172.28.0.17:9200",
        "cluster_status": "green",
        "result": "PASS"
      },
      "log_pipeline": {
        "target": "http://172.28.0.16:9201",
        "elasticsearch": "green",
        "result": "PASS"
      },
      "index_query": {
        "index": "corp-logs-f-037",
        "count": 4560,
        "result": "PASS"
      },
      "result": "PASS",
      "parity_level": "L3",
      "ship": {
        "shipped": true,
        "indexed": 80,
        "index": "corp-logs-f-037",
        "pipeline": {
          "feature_id": "F-037",
          "index": "corp-logs-f-037",
          "indexed": 80
        }
      }
    }
  ],
  "seed_refs": [
    "seeds/real/hris/employees.yml",
    "seeds/real/badge/locations.yml",
    "seeds/real/print/confidential-report.pdf",
    "seeds/real/crm/records.yml",
    "seeds/real/identity/users.csv",
    "seeds/real/files/classification.yml",
    "seeds/real/baseline/normal_day.yml"
  ],
  "anomaly_detected": false,
  "event_count": 4,
  "synthetic_preserved": true,
  "generated_at": "2026-05-23T03:18:39.119293+00:00",
  "stack": "watchtower-corp",
  "result": "PASS",
  "status": "PASS",
  "replay_key": "S-083:9083:negative:real"
}
